[{"form_parameter": {"account": "user", "password": "password", "account_value": "admin", "password_value": "admin"}, "cookie": {"attack": "sessionHijacking", "name": "osclass", "httpOnly": true, "secure": false}, "button": "Log in", "link": "https://app7.com/oc-admin/index.php?page=login"}, {"form_parameter": {"account": "user", "password": "password", "account_value": "admin", "password_value": "admin"}, "cookie": {"attack": "sessionFixation", "name": "osclass", "httpOnly": true, "secure": false}, "button": "Log in", "link": "https://app7.com/oc-admin/index.php?page=login"}, {"form_parameter": {"account": "email", "password": "password", "account_value": "test@test.com", "password_value": "testtest"}, "cookie": {"attack": "sessionHijacking", "name": "osclass", "httpOnly": true, "secure": false}, "link": "https://app7.com/index.php?page=login"}, {"form_parameter": {"account": "email", "password": "password", "account_value": "test@test.com", "password_value": "testtest"}, "cookie": {"attack": "sessionFixation", "name": "osclass", "httpOnly": true, "secure": false}, "link": "https://app7.com/index.php?page=login"}]